mac_notifications/__init__.py
mac_notifications/client.py
mac_notifications/listener_process.py
mac_notifications/manager.py
mac_notifications/notification_config.py
mac_notifications/notification_sender.py
mac_notifications/singleton.py
macos_notifications-0.1.6.dist-info/LICENSE
macos_notifications-0.1.6.dist-info/WHEEL
macos_notifications-0.1.6.dist-info/METADATA
macos_notifications-0.1.6.dist-info/RECORD
